zope.app.file-5.0-py3.11-nspkg.pth
zope/app/file/__init__.py
zope/app/file/configure.zcml
zope/app/file/file.py
zope/app/file/ftesting.zcml
zope/app/file/i18n.py
zope/app/file/image.py
zope/app/file/interfaces.py
zope/app/file/testing.py
zope/app/file/browser/__init__.py
zope/app/file/browser/configure.zcml
zope/app/file/browser/file.py
zope/app/file/browser/file.rst
zope/app/file/browser/file_add.pt
zope/app/file/browser/file_icon.gif
zope/app/file/browser/file_upload.pt
zope/app/file/browser/image.py
zope/app/file/browser/image_edit.pt
zope/app/file/browser/image_icon.gif
zope/app/file/browser/preview.pt
zope/app/file/browser/url.rst
zope/app/file/browser/tests/__init__.py
zope/app/file/browser/tests/test_file.py
zope/app/file/browser/tests/test_functional.py
zope/app/file/browser/tests/test_imagedata.py
zope/app/file/tests/__init__.py
zope/app/file/tests/test_file.py
zope/app/file/tests/test_functional_put.py
zope/app/file/tests/test_image.py
zope.app.file-5.0.dist-info/METADATA
zope.app.file-5.0.dist-info/WHEEL
zope.app.file-5.0.dist-info/namespace_packages.txt
zope.app.file-5.0.dist-info/top_level.txt
zope.app.file-5.0.dist-info/RECORD
