Metadata-Version: 2.1
Name: zope.app.file
Version: 5.0
Summary: File and Image -- Zope 3 Content Components
Home-page: https://github.com/zopefoundation/zope.app.file
Author: Zope Foundation and Contributors
Author-email: zope-dev@zope.org
License: ZPL 2.1
Keywords: zope3 file image content
Classifier: Development Status :: 5 - Production/Stable
Classifier: Environment :: Web Environment
Classifier: Intended Audience :: Developers
Classifier: License :: OSI Approved :: Zope Public License
Classifier: Programming Language :: Python
Classifier: Programming Language :: Python :: 3
Classifier: Programming Language :: Python :: 3.8
Classifier: Programming Language :: Python :: 3.9
Classifier: Programming Language :: Python :: 3.10
Classifier: Programming Language :: Python :: 3.11
Classifier: Programming Language :: Python :: 3.12
Classifier: Programming Language :: Python :: 3.13
Classifier: Programming Language :: Python :: Implementation :: CPython
Classifier: Programming Language :: Python :: Implementation :: PyPy
Classifier: Natural Language :: English
Classifier: Operating System :: OS Independent
Classifier: Topic :: Internet :: WWW/HTTP
Classifier: Framework :: Zope :: 3
Requires-Python: >=3.8
Requires-Dist: setuptools
Requires-Dist: transaction
Requires-Dist: persistent
Requires-Dist: zope.app.content>=4.0.0
Requires-Dist: zope.app.form>=5.0.0
Requires-Dist: zope.app.publication
Requires-Dist: zope.contenttype>=4.0.0
Requires-Dist: zope.datetime
Requires-Dist: zope.dublincore>=4.0.0
Requires-Dist: zope.event
Requires-Dist: zope.exceptions
Requires-Dist: zope.filerepresentation
Requires-Dist: zope.i18nmessageid>=4.1.0
Requires-Dist: zope.interface
Requires-Dist: zope.schema
Requires-Dist: zope.site
Requires-Dist: zope.size
Provides-Extra: test
Requires-Dist: webtest; extra == "test"
Requires-Dist: zope.app.appsetup>=4.0.0; extra == "test"
Requires-Dist: zope.app.basicskin>=4.0.0; extra == "test"
Requires-Dist: zope.app.exception>=4.0.1; extra == "test"
Requires-Dist: zope.app.folder>=4.0.0; extra == "test"
Requires-Dist: zope.app.http>=4.0.1; extra == "test"
Requires-Dist: zope.app.rotterdam>=4.0.0; extra == "test"
Requires-Dist: zope.app.securitypolicy; extra == "test"
Requires-Dist: zope.app.wsgi>=5.3; extra == "test"
Requires-Dist: zope.dublincore; extra == "test"
Requires-Dist: zope.login; extra == "test"
Requires-Dist: zope.principalannotation; extra == "test"
Requires-Dist: zope.publisher>=3.12; extra == "test"
Requires-Dist: zope.testing; extra == "test"
Requires-Dist: zope.testrunner; extra == "test"
